easy_custom_titlebar/__init__.py
easy_custom_titlebar/custom_titlebar.py
easy_custom_titlebar/assets/checklist.ico
easy_custom_titlebar/assets/checklist.png
easy_custom_titlebar/assets/close_black.png
easy_custom_titlebar/assets/close_white.png
easy_custom_titlebar/assets/maximize_black.png
easy_custom_titlebar/assets/maximize_white.png
easy_custom_titlebar/assets/minimize_black.png
easy_custom_titlebar/assets/minimize_white.png
easy_custom_titlebar/assets/restore_black.png
easy_custom_titlebar/assets/restore_white.png
easy_custom_titlebar/assets/your_large_image.png
easy_custom_titlebar-2.0.1.dist-info/licenses/LICENSE
easy_custom_titlebar-2.0.1.dist-info/METADATA
easy_custom_titlebar-2.0.1.dist-info/WHEEL
easy_custom_titlebar-2.0.1.dist-info/top_level.txt
easy_custom_titlebar-2.0.1.dist-info/RECORD
